LICENSE
MANIFEST.in
README.rst
setup.py
orionx_api_client.egg-info/PKG-INFO
orionx_api_client.egg-info/SOURCES.txt
orionx_api_client.egg-info/dependency_links.txt
orionx_api_client.egg-info/not-zip-safe
orionx_api_client.egg-info/requires.txt
orionx_api_client.egg-info/top_level.txt
orionxapi/__init__.py
orionxapi/client.py
orionxapi/transport.py