Metadata-Version: 1.1
Name: orionx-api-client
Version: 1.0.3
Summary: Orionx API Client
Home-page: http://github.com/itolosa/orionx-api-client
Author: Ignacio Tolosa Guerrero
Author-email: ignacio@perejil.cl
License: MIT
Keywords: orionx api client
Platform: UNKNOWN
Classifier: Intended Audience :: Developers
Classifier: License :: OSI Approved :: MIT License
Classifier: Operating System :: OS Independent
Classifier: Programming Language :: Python :: 2
Classifier: Programming Language :: Python :: 2.7
Classifier: Programming Language :: Python :: 3
Classifier: Programming Language :: Python :: 3.3
Classifier: Programming Language :: Python :: 3.4
Classifier: Programming Language :: Python :: 3.5
Classifier: Programming Language :: Python :: 3.6
Classifier: Topic :: Internet :: WWW/HTTP
